frozone/__init__.py
frozone/__main__.py
frozone/frozone.py
frozone/restore.sh
frozone-0.1.1.data/scripts/restore.sh
frozone-0.1.1.dist-info/LICENSE
frozone-0.1.1.dist-info/METADATA
frozone-0.1.1.dist-info/WHEEL
frozone-0.1.1.dist-info/entry_points.txt
frozone-0.1.1.dist-info/top_level.txt
frozone-0.1.1.dist-info/RECORD
