Metadata-Version: 2.1
Name: frozone
Version: 0.1.1
Summary: A tool to save and restore the position of windows using wmctrl
Author-email: Adil Atalay Hamamcioglu <38231748+recoskyler@users.noreply.github.com>
Project-URL: Homepage, https://github.com/recoskyler/frozone
Project-URL: Issues, https://github.com/recoskyler/frozone/issues
Keywords: window manager,window position,gnome,desktop,linux,wmctrl,x11,xorg
Classifier: Programming Language :: Python :: 3
Classifier: License :: OSI Approved :: GNU General Public License v3 (GPLv3)
Classifier: Environment :: Console
Classifier: Natural Language :: English
Classifier: Operating System :: POSIX :: Linux
Classifier: Topic :: Utilities
Classifier: Topic :: Desktop Environment
Classifier: Topic :: Desktop Environment :: Window Managers
Classifier: Development Status :: 4 - Beta
Requires-Python: >=3.2
License-File: LICENSE
Requires-Dist: setuptools
Requires-Dist: Click
